pyblack/__init__.py
pyblack/constants.py
pyblack/gw/__init__.py
pyblack/gw/gw_time.py
pyblack/gw/ext_data/cured_gw_time.interpolation
pyBLACK-0.0.5.dev0.dist-info/LICENSE
pyBLACK-0.0.5.dev0.dist-info/METADATA
pyBLACK-0.0.5.dev0.dist-info/WHEEL
pyBLACK-0.0.5.dev0.dist-info/top_level.txt
pyBLACK-0.0.5.dev0.dist-info/RECORD
